doris_mcp_server/__init__.py
doris_mcp_server/__main__.py
doris_mcp_server/main.py
doris_mcp_server/tools/__init__.py
doris_mcp_server/tools/prompts_manager.py
doris_mcp_server/tools/resources_manager.py
doris_mcp_server/tools/tools_manager.py
doris_mcp_server/utils/__init__.py
doris_mcp_server/utils/analysis_tools.py
doris_mcp_server/utils/config.py
doris_mcp_server/utils/db.py
doris_mcp_server/utils/logger.py
doris_mcp_server/utils/monitoring_tools.py
doris_mcp_server/utils/query_executor.py
doris_mcp_server/utils/schema_extractor.py
doris_mcp_server/utils/security.py
mcp_doris_server-0.4.2.dist-info/METADATA
mcp_doris_server-0.4.2.dist-info/WHEEL
mcp_doris_server-0.4.2.dist-info/entry_points.txt
mcp_doris_server-0.4.2.dist-info/licenses/LICENSE.txt
mcp_doris_server-0.4.2.dist-info/RECORD
