Metadata-Version: 2.4
Name: mcp-doris-server
Version: 0.4.2
Summary: Enterprise-grade Model Context Protocol (MCP) server implementation for Apache Doris
Project-URL: Homepage, https://github.com/apache/doris-mcp-server
Project-URL: Documentation, https://doris.apache.org/docs/
Project-URL: Repository, https://github.com/apache/doris-mcp-server.git
Project-URL: Issues, https://github.com/apache/doris-mcp-server/issues
Project-URL: Changelog, https://github.com/apache/doris-mcp-server/blob/main/CHANGELOG.md
Author-email: Yijia Su <freeoneplus@apache.org>
License: Apache-2.0
License-File: LICENSE.txt
Keywords: analytics,database,doris,mcp,model-context-protocol
Classifier: Development Status :: 4 - Beta
Classifier: Intended Audience :: Developers
Classifier: License :: OSI Approved :: Apache Software License
Classifier: Operating System :: OS Independent
Classifier: Programming Language :: Python :: 3.12
Classifier: Topic :: Database
Classifier: Topic :: Scientific/Engineering :: Information Analysis
Classifier: Topic :: Software Development :: Libraries :: Python Modules
Requires-Python: >=3.12
Requires-Dist: aiofiles>=23.0.0
Requires-Dist: aiohttp>=3.9.0
Requires-Dist: aiomysql>=0.2.0
Requires-Dist: aioredis>=2.0.0
Requires-Dist: asyncio-mqtt>=0.16.0
Requires-Dist: bcrypt>=4.1.0
Requires-Dist: click>=8.1.0
Requires-Dist: cryptography>=41.0.0
Requires-Dist: fastapi>=0.108.0
Requires-Dist: httpx>=0.26.0
Requires-Dist: mcp<2.0.0,>=1.8.0
Requires-Dist: numpy>=1.24.0
Requires-Dist: orjson>=3.9.0
Requires-Dist: pandas>=2.0.0
Requires-Dist: passlib[bcrypt]>=1.7.0
Requires-Dist: prometheus-client>=0.19.0
Requires-Dist: pydantic-settings>=2.1.0
Requires-Dist: pydantic>=2.5.0
Requires-Dist: pyjwt>=2.8.0
Requires-Dist: pymysql>=1.1.0
Requires-Dist: pytest-asyncio>=1.0.0
Requires-Dist: pytest-cov>=6.1.1
Requires-Dist: pytest>=8.4.0
Requires-Dist: python-dateutil>=2.8.0
Requires-Dist: python-dotenv>=1.0.0
Requires-Dist: python-jose[cryptography]>=3.3.0
Requires-Dist: python-multipart>=0.0.6
Requires-Dist: pyyaml>=6.0.0
Requires-Dist: requests>=2.31.0
Requires-Dist: rich>=13.7.0
Requires-Dist: sqlparse>=0.4.4
Requires-Dist: starlette>=0.27.0
Requires-Dist: structlog>=23.2.0
Requires-Dist: toml>=0.10.0
Requires-Dist: tqdm>=4.66.0
Requires-Dist: typer>=0.9.0
Requires-Dist: uvicorn[standard]>=0.25.0
Requires-Dist: websockets>=12.0
Provides-Extra: dev
Requires-Dist: bandit>=1.7.0; extra == 'dev'
Requires-Dist: black>=23.12.0; extra == 'dev'
Requires-Dist: flake8>=7.0.0; extra == 'dev'
Requires-Dist: isort>=5.13.0; extra == 'dev'
Requires-Dist: mypy>=1.8.0; extra == 'dev'
Requires-Dist: myst-parser>=2.0.0; extra == 'dev'
Requires-Dist: pre-commit>=3.6.0; extra == 'dev'
Requires-Dist: pytest-asyncio>=0.23.0; extra == 'dev'
Requires-Dist: pytest-cov>=4.1.0; extra == 'dev'
Requires-Dist: pytest-mock>=3.12.0; extra == 'dev'
Requires-Dist: pytest-xdist>=3.5.0; extra == 'dev'
Requires-Dist: pytest>=7.4.0; extra == 'dev'
Requires-Dist: ruff>=0.1.0; extra == 'dev'
Requires-Dist: safety>=2.3.0; extra == 'dev'
Requires-Dist: sphinx-rtd-theme>=2.0.0; extra == 'dev'
Requires-Dist: sphinx>=7.2.0; extra == 'dev'
Requires-Dist: tox>=4.11.0; extra == 'dev'
Provides-Extra: docs
Requires-Dist: myst-parser>=2.0.0; extra == 'docs'
Requires-Dist: sphinx-autoapi>=3.0.0; extra == 'docs'
Requires-Dist: sphinx-rtd-theme>=2.0.0; extra == 'docs'
Requires-Dist: sphinx>=7.2.0; extra == 'docs'
Provides-Extra: monitoring
Requires-Dist: grafana-client>=3.5.0; extra == 'monitoring'
Requires-Dist: jaeger-client>=4.8.0; extra == 'monitoring'
Requires-Dist: opentelemetry-api>=1.21.0; extra == 'monitoring'
Requires-Dist: opentelemetry-sdk>=1.21.0; extra == 'monitoring'
Requires-Dist: prometheus-client>=0.19.0; extra == 'monitoring'
Provides-Extra: performance
Requires-Dist: cchardet>=2.1.0; extra == 'performance'
Requires-Dist: orjson>=3.9.0; extra == 'performance'
Requires-Dist: uvloop>=0.19.0; extra == 'performance'
